hwloc_xml_parser/__init__.py
hwloc_xml_parser/topology.cpython-311-aarch64-linux-gnu.so
hwloc_xml_parser/topology.py
hwloc_xml_parser/topology__mypyc.cpython-311-aarch64-linux-gnu.so
hwloc_xml_parser-0.0.4.dist-info/METADATA
hwloc_xml_parser-0.0.4.dist-info/WHEEL
hwloc_xml_parser-0.0.4.dist-info/top_level.txt
hwloc_xml_parser-0.0.4.dist-info/RECORD
hwloc_xml_parser-0.0.4.dist-info/licenses/LICENSE
