Metadata-Version: 2.4
Name: hwloc-xml-parser
Version: 0.0.4
Summary: Parse xml output of hwloc.
Author: Arnst Maarten, Tomasetti Romin
License-Expression: MIT
Project-URL: Homepage, https://github.com/uliegecsm/hwloc-xml-parser
Project-URL: Documentation, https://uliegecsm.github.io/hwloc-xml-parser/
Requires-Python: >=3.10
License-File: LICENSE
Dynamic: license-file
